MANIFEST.in
README.md
requirements.txt
setup.py
config/pypi/__init__.py
ga-master/.gitignore
ga-master/.travis.yml
ga-master/CHANGELOG.md
ga-master/CMakeLists.txt
ga-master/COPYRIGHT
ga-master/INSTALL
ga-master/Makefile.am
ga-master/README.md
ga-master/autogen.sh
ga-master/configure.ac
ga-master/version.sh
ga-master/LinAlg/lapack+blas/CMakeLists.txt
ga-master/LinAlg/lapack+blas/README
ga-master/LinAlg/lapack+blas/dummy.c
ga-master/LinAlg/lapack+blas/gal_cgemm.f
ga-master/LinAlg/lapack+blas/gal_daxpy.f
ga-master/LinAlg/lapack+blas/gal_dcabs1.f
ga-master/LinAlg/lapack+blas/gal_dcopy.f
ga-master/LinAlg/lapack+blas/gal_ddot.f
ga-master/LinAlg/lapack+blas/gal_dgemm.f
ga-master/LinAlg/lapack+blas/gal_dgemv.f
ga-master/LinAlg/lapack+blas/gal_dger.f
ga-master/LinAlg/lapack+blas/gal_dgetf2.f
ga-master/LinAlg/lapack+blas/gal_dgetrf.f
ga-master/LinAlg/lapack+blas/gal_dgetrs.f
ga-master/LinAlg/lapack+blas/gal_disnan.f
ga-master/LinAlg/lapack+blas/gal_dlacpy.f
ga-master/LinAlg/lapack+blas/gal_dlae2.f
ga-master/LinAlg/lapack+blas/gal_dlaev2.f
ga-master/LinAlg/lapack+blas/gal_dlaisnan.f
ga-master/LinAlg/lapack+blas/gal_dlamch.f
ga-master/LinAlg/lapack+blas/gal_dlanst.f
ga-master/LinAlg/lapack+blas/gal_dlansy.f
ga-master/LinAlg/lapack+blas/gal_dlapy2.f
ga-master/LinAlg/lapack+blas/gal_dlarf.f
ga-master/LinAlg/lapack+blas/gal_dlarfb.f
ga-master/LinAlg/lapack+blas/gal_dlarfg.f
ga-master/LinAlg/lapack+blas/gal_dlarft.f
ga-master/LinAlg/lapack+blas/gal_dlartg.f
ga-master/LinAlg/lapack+blas/gal_dlascl.f
ga-master/LinAlg/lapack+blas/gal_dlaset.f
ga-master/LinAlg/lapack+blas/gal_dlasr.f
ga-master/LinAlg/lapack+blas/gal_dlasrt.f
ga-master/LinAlg/lapack+blas/gal_dlassq.f
ga-master/LinAlg/lapack+blas/gal_dlaswp.f
ga-master/LinAlg/lapack+blas/gal_dlatrd.f
ga-master/LinAlg/lapack+blas/gal_dnrm2.f
ga-master/LinAlg/lapack+blas/gal_dorg2l.f
ga-master/LinAlg/lapack+blas/gal_dorg2r.f
ga-master/LinAlg/lapack+blas/gal_dorgql.f
ga-master/LinAlg/lapack+blas/gal_dorgqr.f
globalarrays.egg-info/PKG-INFO
globalarrays.egg-info/SOURCES.txt
globalarrays.egg-info/dependency_links.txt
globalarrays.egg-info/requires.txt
globalarrays.egg-info/top_level.txt
