Metadata-Version: 2.1
Name: globalarrays
Version: 5.7.1b0
Summary: globalarrays: Global Arrays Toolkit
Home-page: https://hpc.pnl.gov/globalarrays/
Author: Jarek Nieplocha, Bruce Palmer, Vinod Tipparaju, Manojkumar Krishnan, Harold Trease, and Edo Apra
Author-email: hpctools@googlegroups.com
Maintainer: Roberto Vidmar
Maintainer-email: rvidmar@inogs.it
License: BSD
Download-URL: https://hpc.pnl.gov/globalarrays/download.shtml
Keywords: GlobalArrays,MPI
Platform: POSIX
Classifier: Development Status :: 4 - Beta
Classifier: Intended Audience :: Developers
Classifier: Intended Audience :: Science/Research
Classifier: License :: OSI Approved :: BSD License
Classifier: Operating System :: POSIX
Classifier: Programming Language :: C
Classifier: Programming Language :: C++
Classifier: Programming Language :: Fortran
Classifier: Programming Language :: Python
Classifier: Topic :: Scientific/Engineering
Classifier: Topic :: Software Development :: Libraries
